riscvmodel/__init__.py
riscvmodel/code.py
riscvmodel/csrnames.py
riscvmodel/golden.py
riscvmodel/insn.py
riscvmodel/isa.py
riscvmodel/model.py
riscvmodel/random.py
riscvmodel/regnames.py
riscvmodel/sim.py
riscvmodel/types.py
riscvmodel/variant.py
riscvmodel/version.py
riscvmodel/program/__init__.py
riscvmodel/program/tests.py
riscvmodel/program/tests_atomic.py
riscv_model-0.6.6.dist-info/LICENSE
riscv_model-0.6.6.dist-info/METADATA
riscv_model-0.6.6.dist-info/WHEEL
riscv_model-0.6.6.dist-info/entry_points.txt
riscv_model-0.6.6.dist-info/top_level.txt
riscv_model-0.6.6.dist-info/RECORD
