Metadata-Version: 2.1
Name: riscv-model
Version: 0.6.6
Summary: RISC-V Model
Home-page: https://github.com/wallento/riscv-python-model
Author: Stefan Wallentowitz
Author-email: stefan@wallentowitz.de
License: UNKNOWN
Platform: UNKNOWN
Classifier: Programming Language :: Python :: 3
Classifier: License :: OSI Approved :: MIT License
Classifier: Operating System :: OS Independent
Provides-Extra: docs
Requires-Dist: sphinx ; extra == 'docs'
Requires-Dist: python-docs-theme ; extra == 'docs'
Requires-Dist: sphinx-argparse ; extra == 'docs'
